{
  "filename": "tutorials\\gamestudio\\3-navigating-scene.md.xlf",
  "files": [
    {
      "\/D:\/repos\/stride-translations\/pt-BR\/source\/tutorials\/gamestudio\/3-navigating-scene.md": [
        [
          "Navigating in the scene editor",
          "Navegando no editor de cena",
          "Navigating in the scene editor",
          "\/D:\/repos\/stride-translations\/pt-BR\/source\/tutorials\/gamestudio\/3-navigating-scene.md",
          {
            "id": "tu1"
          }
        ],
        [
          "In this tutorial we learn how to navigate around the scene editor.",
          "Neste tutorial aprendemos como navegar pelo editor de cena.",
          "In this tutorial we learn how to navigate around the scene editor.",
          "\/D:\/repos\/stride-translations\/pt-BR\/source\/tutorials\/gamestudio\/3-navigating-scene.md",
          {
            "id": "tu2"
          }
        ],
        [
          "We also take a look at the various camera options.",
          "Também analisamos as várias opções de câmera.",
          " We also take a look at the various camera options.",
          "\/D:\/repos\/stride-translations\/pt-BR\/source\/tutorials\/gamestudio\/3-navigating-scene.md",
          {
            "id": "tu2"
          }
        ],
        [
          "[!INCLUDE <g1>stride-studio-note<\/g1>]",
          "[! INCLUÍDO <g1>stride-studio-note<\/g1>]",
          "[!INCLUDE <g1>stride-studio-note<\/g1>]",
          "\/D:\/repos\/stride-translations\/pt-BR\/source\/tutorials\/gamestudio\/3-navigating-scene.md",
          {
            "id": "tu3"
          }
        ],
        [
          "<x1\/>!Video https:\/\/www.youtube.com\/embed\/lGQ607bT6gk<x2\/>",
          "<x1\/>!Vídeo https:\/\/www.youtube.com\/embed\/lGQ607bT6gk<x2\/>",
          "<x1\/>!Video https:\/\/www.youtube.com\/embed\/lGQ607bT6gk<x2\/>",
          "\/D:\/repos\/stride-translations\/pt-BR\/source\/tutorials\/gamestudio\/3-navigating-scene.md",
          {
            "id": "tu4"
          }
        ]
      ]
    }
  ],
  "seg_enabled": false
}